jpyutils/__init__.py
jpyutils/mlutils/__init__.py
jpyutils/mlutils/tags.py
jpyutils/mlutils/text.py
jpyutils/network/__init__.py
jpyutils/network/email.py
jpyutils/network/netdata.py
jpyutils/runner/__init__.py
jpyutils/runner/common.py
jpyutils/runner/multi_task_runner.py
jpyutils/runner/proc_runner.py
jpyutils/runner/progress_display.py
jpyutils/runner/task_runner.py
jpyutils/utils/__init__.py
jpyutils/utils/deprecation.py
jpyutils/utils/disk.py
jpyutils/utils/random.py
jpyutils/utils/terminal.py
jpyutils-0.1.1.dist-info/LICENSE
jpyutils-0.1.1.dist-info/METADATA
jpyutils-0.1.1.dist-info/WHEEL
jpyutils-0.1.1.dist-info/top_level.txt
jpyutils-0.1.1.dist-info/RECORD
