Metadata-Version: 2.1
Name: jpyutils
Version: 0.1.1
Summary: To make daily work and study more efficient
Home-page: https://github.com/zero91/jpyutils
Author: Donald Cheung
Author-email: jianzhang9102@gmail.com
License: UNKNOWN
Platform: UNKNOWN
Classifier: Programming Language :: Python :: 3
Classifier: License :: OSI Approved :: GNU Lesser General Public License v3 (LGPLv3)
Classifier: Operating System :: OS Independent
Requires-Python: >=3.5
Requires-Dist: requests (>=2.20.0)
Requires-Dist: jieba
Requires-Dist: numpy
